mikan_rs-0.1.4.dist-info/METADATA
mikan_rs-0.1.4.dist-info/WHEEL
mikan_rs-0.1.4.dist-info/licenses/LICENSE-APACHE
mikan_rs-0.1.4.dist-info/licenses/LICENSE-MIT
mikan/__init__.py
mikan/alias.py
mikan/metrics.py
mikan/_mikan.cpython-312-x86_64-linux-gnu.so
mikan_rs-0.1.4.dist-info/RECORD
