Metadata-Version: 2.4
Name: mikan-rs
Version: 0.1.4
Classifier: Programming Language :: Rust
Classifier: Programming Language :: Python :: Implementation :: CPython
Requires-Dist: numpy
Requires-Dist: simpleitk
License-File: LICENSE-APACHE
License-File: LICENSE-MIT
Summary: A medical image kit for segmentation metrics evaluation, native Rust support, and Python bindings for cross-language performance.
Keywords: medical-imaging,metrics,nifti,nibabel,ITK
License: MIT OR Apache-2.0
Requires-Python: >=3.8
Project-URL: Source Code, https://github.com/Plasma-Blue/mikan-rs
